{
  "categorias": [
    {
      "id": 1,
      "nombre": "Deportiva"
    },
    {
      "id": 2,
      "nombre": "Minimoto"
    },
    {
      "id": 3,
      "nombre": "Motoneta"
    },
    {
      "id": 4,
      "nombre": "Motocarro"
    }
  ],
  "productos": [
    {
      "id": 1,
      "image": "https://upload.wikimedia.org/wikipedia/commons/thumb/8/8a/Yamaha_YZF-R6_bleue.jpg/1200px-Yamaha_YZF-R6_bleue.jpg",
      "video": "https://www.youtube.com/embed/OYrzPms5F38",
      "price": "2000",
      "title": "Yamaha YZF-R6",
      "category": "Deportiva",
      "description": "Motocicleta de gran velocidad"
    },
    {
      "id": 2,
      "image": "https://lh3.googleusercontent.com/proxy/0QTTxAoLGYwz-h6xuzxoqNsimRWIzJvBaAc7TdnjcSZYQ8PlTapsbAReEuOZQoL4GtNLmNUD7bqtraK60Y3vtwTJ8oRIxwXCZWlJZ_u1a13gYto7Eq2a2G8nOIUnUVK1eYBNKD9APQQpaA",
      "video": "https://www.youtube.com/embed/NgnhIO3Bpzo",
      "price": "800",
      "title": "Serpento naga",
      "category": "Deportiva",
      "description": "color blanco, motor monocilindrico"
    },
    {
      "id": 3,
      "image": "https://www.motofichas.com/images/phocagallery/Kawasaki/J300_2017/01-kawasaki-j300-2017.jpg",
	  "video": "https://www.youtube.com/embed/j_s_4YjTOHg",
      "price": "695.00",
      "title": "Kawasaki J300",
      "category": "Motoneta",
      "description": "color negra, motor monocilindrico"
    },
    {
      "id": 6,
      "image": "https://s3.eu-west-1.amazonaws.com/cdn.motorbikemag.es/wp-content/uploads/2017/08/Harley-Davidson-CVO-Limited-2018-01-530x397.jpg",
      "video": "https://www.youtube.com/embed/tRx6s3_53f4",
      "price": "178",
      "title": "Harley-davidson cvo",
      "category": "Deportiva",
      "description": "color azul, motor de 2 cilindros"
    },
    {
      "id": 7,
      "image": "http://www.vespaoficial.com.ar/img/modelos/sprint/sprint_s-gris.png",
	  "video": "https://www.youtube.com/embed/nVAOl9hRG9c",
      "price": "500",
      "title": "vespa gris",
      "category": "Motoneta",
      "description": "color gris, motor monocilindrico"
    },
    {
      "id": 8,
      "image": "https://www.techgames.com.mx/wp-content/uploads/2019/11/Honda-NAVi-Mexico-Negra.jpg",
	  "video": "https://www.youtube.com/watch?v=ud8s2Pgaae0",
      "price": "400",
      "title": "Honda navi",
      "category": "Minimoto",
      "description": "color negro, motor monocilidrico"
    },
    {
      "id": 9,
      "image": "https://i0.wp.com/yamahaizabal.com/wp-content/uploads/2020/06/ybr125zr1-1.jpg",
	  "video": "https://www.youtube.com/embed/YZ5rsViU-Qw",
      "price": "1200",
      "title": "Yamaha YBR",
      "category": "Deportiva",
      "description": "color motor"
    },
    {
      "id": 10,
      "image": "https://www.blogdecoches.net/wp-content/uploads/2018/09/Honda-01.jpg",
	  "video": "https://www.youtube.com/embed/k5yFKxBxmT0",
      "price": "109.00",
      "title": "Honda XR190L",
      "category": "Deportiva",
      "description": "color blanco, motor monocilindrico"
    },
    {
      "id": 11,
      "image": "https://www.yamaha-motor.com.mx/images/motos/fazer_2021_n3.jpg",
	  "video": "https://www.youtube.com/embed/J4dMCwCxJIw",
      "price": "900.00",
      "title": "Yamaha Fazer Fi",
      "category": "Deportiva",
      "description": "color negro, motor monocilindrico"
    },
    {
      "id": 12,
      "image": "https://placervial.com/wp-content/uploads/2019/11/cryptonFI-01-1024x640.jpg",
	  "video": "https://www.youtube.com/embed/lh7E7MnGCUM",
      "price": "114.00",
      "title": "Yamaha crypton",
      "category": "Motoneta",
      "description": "color negro, motor monocilindrico"
    },
    {
      "id": 13,
      "image": "https://w0.peakpx.com/wallpaper/471/766/HD-wallpaper-yamaha-art-concept-motorbikes-tesseract.jpg",
	  "video": "https://www.youtube.com/embed/2jvD406RkCk", 
      "price": "599.00",
      "title": "Yamaha Tesseract",
      "category": "Deportiva",
      "description": "color blanco, motor monocilindrico"
    },
    {
      "id": 14,
      "image": "http://3.bp.blogspot.com/--3FX-zlk5No/U6zE6EBSesI/AAAAAAAAAWY/z6OcTpDNdA8/s1600/CARGUERO+VERDE.jpg",
	  "video": "https://www.youtube.com/embed/yYkimeIw9ks",
      "price": "999.99",
      "title": "Mototriciclo 250cc",
      "category": "Motocarro",
      "description": "color verde, motor monocilindrico"
    },
    {
      "id": 15,
      "image": "https://progreser.com/wp-content/uploads/2020/12/NINJA-400-Kawasaki-BLANCA-Motos-Zoom-ProgreSER.jpg",
	  "video": "https://www.youtube.com/embed/go8WpJNT-hE",
      "price": "800.00",
      "title": "Kawasaki ninja",
      "category": "Minimoto",
      "description": "color blanca, motor bicilindrico"
    },
    {
      "id": 16,
      "image": "https://www.demotos.com.co/wp-content/uploads/2021/10/Pulsar-250-por.jpg",
	  "video": "https://www.youtube.com/embed/UCDG6rApvN0",
      "price": "500",
      "title": "Pulsar NS250",
      "category": "Deportiva",
      "description": "color rojo, motor monocilindrico"
    },
    {
      "id": 17,
      "image": "https://i.pinimg.com/originals/8a/e6/89/8ae689d252eb1d0df72eed74e075053c.jpg",
	  "video": "https://www.youtube.com/embed/I7CemjQSHx8",
      "price": "650.0",
      "title": "Honda tornado XR 250",
      "category": "Deportiva",
      "description": "color rojo, motor monocilindrico"
    },
    {
      "id": 18,
      "image": "https://s3.eu-west-1.amazonaws.com/cdn.motorbikemag.es/wp-content/uploads/2020/10/Kawasaki-Z650-2021-13.jpg",
	  "video": "https://www.youtube.com/embed/tYsLh0bEw3w",
      "price": "600",
      "title": "Kawasaki Z650",
      "category": "Minimoto",
      "description": "color negra, motor bicilindrico"
    },
    {
      "id": 19,
      "image": "https://www.prado.com.sv/media/catalog/product/m/o/motocicleta-serpento-defender-150-2022precio-si-incluye-gastos-de-inscripcion-negro-blanco-171343-1-lateral-izquierda.jpg?quality=80&bg-color=255,255,255&fit=bounds&height=&width=",
	  "video": "https://www.youtube.com/embed/QSpnG7HXBhY",
      "price": "700",
      "title": "Serpento defender",
      "category": "Deportiva",
      "description": "color blanco, motor de 4 tiempos"
    },
    {
      "id": 20,
      "image": "https://www.harley-davidson.com/content/dam/h-d/images/product-images/bikes/motorcycle/2021/2021-iron-883/2021-iron-883-f24/360/2021-iron-883-f24-motorcycle-08.jpg?impolicy=myresize&rw=1600",
	  "video": "https://www.youtube.com/embed/GJC0yPUvo_Y",
      "price": "1500",
      "title": "harley Davidson iron 883",
      "category": "Deportiva",
      "description": "color negra, motor bicilindrico"
    },
    {
      "id": "2",
      "image": "https://www.motoroads.com/photos/big-front-view-harley-davidson-sport-glide-rent-a-motorbike-in-geneva.jpeg",
      "video": "https://www.youtube.com/embed/LMeOz0JmpjI",
      "price": "1400",
      "title": "Harley Davidson sport glide",
      "category": "Deportiva",
      "description": "color negro, motor bicilindrico"
    }
  ]
}